planetmapper/__init__.py
planetmapper/__main__.py
planetmapper/_assets.py
planetmapper/base.py
planetmapper/basic_body.py
planetmapper/body.py
planetmapper/body_xy.py
planetmapper/cli.py
planetmapper/common.py
planetmapper/data_loader.py
planetmapper/gui.py
planetmapper/kernel_downloader.py
planetmapper/observation.py
planetmapper/progress.py
planetmapper/py.typed
planetmapper/utils.py
planetmapper/assets/gui_icon.png
planetmapper/data/ring_aliases.json
planetmapper/data/rings.json
planetmapper-1.13.4.dist-info/licenses/LICENSE.txt
planetmapper-1.13.4.dist-info/METADATA
planetmapper-1.13.4.dist-info/WHEEL
planetmapper-1.13.4.dist-info/entry_points.txt
planetmapper-1.13.4.dist-info/top_level.txt
planetmapper-1.13.4.dist-info/RECORD
