Metadata-Version: 2.4
Name: planetmapper
Version: 1.13.4
Summary: PlanetMapper: A Python package for visualising, navigating and mapping Solar System observations
Home-page: https://github.com/ortk95/planetmapper
Download-URL: https://pypi.org/project/planetmapper/
Author: Oliver King
Author-email: oliver.king95@gmail.com
License: MIT
Project-URL: Documentation, https://planetmapper.readthedocs.io/
Project-URL: GitHub, https://github.com/ortk95/planetmapper
Project-URL: Changelog, https://github.com/ortk95/planetmapper/releases
Project-URL: Paper, https://doi.org/10.21105/joss.05728
Project-URL: conda-forge, https://anaconda.org/conda-forge/planetmapper
Keywords: planetmapper,astronomy,space,science,spice,ephemeris,planetary-science,geometry
Classifier: Development Status :: 5 - Production/Stable
Classifier: License :: OSI Approved :: MIT License
Classifier: Programming Language :: Python :: 3.10
Classifier: Programming Language :: Python :: 3.11
Classifier: Programming Language :: Python :: 3.12
Classifier: Programming Language :: Python :: 3.13
Classifier: Topic :: Scientific/Engineering
Classifier: Topic :: Scientific/Engineering :: Astronomy
Classifier: Topic :: Scientific/Engineering :: Visualization
Classifier: Topic :: Scientific/Engineering :: Physics
Classifier: Framework :: Matplotlib
Requires-Python: >=3.10.0
License-File: LICENSE.txt
Requires-Dist: astropy
Requires-Dist: matplotlib
Requires-Dist: numpy
Requires-Dist: Pillow
Requires-Dist: spiceypy
Requires-Dist: scipy
Requires-Dist: photutils
Requires-Dist: tqdm
Requires-Dist: pyproj
Requires-Dist: typing-extensions
Dynamic: author
Dynamic: author-email
Dynamic: classifier
Dynamic: description
Dynamic: description-content-type
Dynamic: download-url
Dynamic: home-page
Dynamic: keywords
Dynamic: license
Dynamic: license-file
Dynamic: project-url
Dynamic: requires-dist
Dynamic: requires-python
Dynamic: summary
